duckrun/__init__.py
duckrun/auth.py
duckrun/core.py
duckrun/ducklake_metadata.py
duckrun/files.py
duckrun/lakehouse.py
duckrun/notebook.py
duckrun/rle.py
duckrun/runner.py
duckrun/semantic_model.py
duckrun/stats.py
duckrun/writer.py
duckrun-0.2.20.dist-info/licenses/LICENSE
duckrun-0.2.20.dist-info/METADATA
duckrun-0.2.20.dist-info/WHEEL
duckrun-0.2.20.dist-info/top_level.txt
duckrun-0.2.20.dist-info/RECORD
