Metadata-Version: 2.4
Name: duckrun
Version: 0.2.20
Summary: Helper library for Fabric Python using duckdb, arrow and delta_rs (orchestration, queries, etc.)
Author: mim
License: MIT
Project-URL: Homepage, https://github.com/djouallah/duckrun
Project-URL: Repository, https://github.com/djouallah/duckrun
Project-URL: Issues, https://github.com/djouallah/duckrun/issues
Requires-Python: >=3.9
License-File: LICENSE
Requires-Dist: duckdb>=1.2.0
Requires-Dist: deltalake<=0.18.2
Requires-Dist: requests>=2.28.0
Requires-Dist: obstore>=0.2.0
Provides-Extra: local
Requires-Dist: azure-identity>=1.12.0; extra == "local"
Dynamic: license-file
